{"name": "John, Bruce and beer", "text": "John, Bruce and beer\nJohn has some money. Bruce has some money too. They know price of a bottle of beer (unfortunately, beer is not free). How many bottles of beer can they buy, if they put together their money?\nInput\nThe first row of input contains John’s amount of money. The second row contains Bruce’s amount of money. The third line contains the price of a bottle of beer. Each amount or price is represented by non-empty integer part, decimal point and exactly two digits after point. Each (John and Bruce’s) amount of money is non-negative and strictly less than 1000000.00. Beer is not free and costs strictly less than 1000.00.\nOutput\nYour program should write exactly one integer: the maximal quantity of bottles guys can buy spending their money.", "compiler": "Judge C++", "send_date": "10 янв. 2017 г., 23:16:38", "time": 3.33, "memory": 676, "code": "#include <bits/stdc++.h>\nusing namespace std;\nint main()\n{\n    long double a,b,c,sum;\n    cin >> a >> b >> c;\n     sum = a+b; \n     a/=c;\n     b/=c;\n     a+=b;\n     cout <<setprecision(0) << fixed << a-0.499 << endl;\n}", "link": "https://www.e-olymp.com/ru/problems/3757"}