{"name": "Формула Герона", "text": "Формула Герона\nЗадано стороны a, b, c, d и диагональ f выпуклого четырехугольника. Определить площадь четырехугольника, используя вспомогательную функцию вычисления площади треугольника по формуле Герона.\nВходные данные\nВ одной строке задано 5 действительных чисел a, b, с, d, f (0 < a, b, c, d, f ≤ 100), как показано на рисунке.\nВыходные данные\nВывести площадь четырехугольника с точностью 4 знака после десятичной точки.", "compiler": "Judge C++", "send_date": "24 апр. 2017 г., 19:53:18", "time": 1.87, "memory": 1784, "code": "#include <bits/stdc++.h>\n#include <math.h>\n#define M_PI 3.1415926535897932384626433832795\nusing namespace std;\nint main()\n{\n    double a,b,c,d,f,p1,p2,s1,s2;\n    cin >> a >> b >> c >> d >> f;\n    p1 = (a+b+f)/2;\n    p2 = (d+c+f)/2;\n    s1 = sqrt(p1*(p1-a)*(p1-b)*(p1-f));\n    s2 = sqrt(p2*(p2-d)*(p2-f)*(p2-c));\n    cout << fixed << setprecision(4) << (s1+s2) << endl;\n}", "link": "https://www.e-olymp.com/ru/problems/926"}