{"name": "Трехзначные числа", "text": "Трехзначные числа\nНайти все трехзначные числа, сумма цифр которых равна n.\nВходные данные\nОдно число n (0 ≤ n ≤ 28).\nВыходные данные\nВ первой строке выведите количество найденных трехзначных чисел. В следующих строках выведите сами трехзначные числа в порядке возрастания.", "compiler": "Judge C++", "send_date": "19 апр. 2017 г., 12:11:17", "time": 2.28, "memory": 1744, "code": "#include <bits/stdc++.h>\nusing namespace std;\nint sumOfN(int n)\n{\n    int i = 0,sum = 0;\n    while(n > 0)\n    {\n        sum+=n%10;\n        n/=10;\n        i++;\n\n    }\n    return sum;\n}\nint main()\n{\n    int n;\n    vector <int> ans;\n    cin >> n;\n    for(int i = 100; i <= 999;i++)\n        if(sumOfN(i) == n)\n            ans.push_back(i);\n    cout << ans.size() << endl;\n    for(int i = 0; i < ans.size(); i++)\n        cout << ans[i] << endl;\n\n\n}", "link": "https://www.e-olymp.com/ru/problems/4101"}