{"name": "Сервер", "text": "Сервер\nВы отвечаете за сервер, на котором необходимо выполнить несколько задач по принципу первый пришел - первый выполнен. Каждый день для выполнения этих задач Вы можете выделить на сервере более t минут. Зная время выполнения каждой задачи, Вы хотите определить, сколько задач будут выполнены сегодня.\nРассмотрим следующий пример. Пусть t = 180, время выполнения задач равны 45, 30, 55, 20, 80 и 20 минут (именно в таком порядке). Только четыре задания могут быть выполнены. На выполнение первых четырех задач следует потратить 150 минут. Пять заданий выполнить нельзя, так как тогда потребуется 230 минут, что больше 180. Несмотря на то что еще останется время на выполнение шестой задачи (на которую требуется 20 минут), после четвертой задачи нельзя выполнить шестую, так как пятая еще не совершена.\nВходные данные\nПервая строка содержит два целых числа n (1 ≤ n ≤ 50) и t (1 ≤ t ≤ 500), где n - количество задач. Следующая строка содержит n натуральных чисел, не больших 100, указывающих на время выполнения каждой задачи.\nВыходные данные\nВывести количество задач, которое может быть выполнено за t минут по принципу первый пришел - первый выполнен.", "compiler": "Judge C++", "send_date": "15 окт. 2017 г., 13:27:04", "time": 2.35, "memory": 1796, "code": "#include <bits/stdc++.h>\nusing namespace std;\nint main()\n{\n    freopen(\"input.txt\",\"r\",stdin);\n    freopen(\"output.txt\",\"w\",stdout);\n    int n,t,sum=0,c=0;\n    cin >> n >> t;\n    vector <int> d(n);\n    int i;\n    for(i=0;i<n;i++){\n        cin >> d[i];\n    }\n    for(i=0;i<n;i++)\n    {\n        sum+=d[i];\n        if(sum > t)\n            break;\n        c++;\n    }\n    cout << c << endl;\n}", "link": "https://www.e-olymp.com/ru/problems/7526"}